cnlunardate.py
cnlunardate-0.0.4.dist-info/LICENSE.txt
cnlunardate-0.0.4.dist-info/METADATA
cnlunardate-0.0.4.dist-info/WHEEL
cnlunardate-0.0.4.dist-info/top_level.txt
cnlunardate-0.0.4.dist-info/RECORD
