Metadata-Version: 2.1
Name: cnlunardate
Version: 0.0.4
Summary: A Chinese lunar date Python library
Home-page: https://github.com/YuBPan/cnlunardate
Author: Y.B. Pan
Author-email: yb.pan@yahoo.com
License: UNKNOWN
Keywords: Chinese lunar date
Platform: UNKNOWN
Classifier: Programming Language :: Python :: 3
Classifier: License :: OSI Approved :: MIT License
Classifier: Operating System :: OS Independent
Requires-Python: >=3.6
